labelops/LabelOps.py
labelops/__init__.py
labelops/version.py
labelops-0.0.0.dist-info/LICENSE
labelops-0.0.0.dist-info/METADATA
labelops-0.0.0.dist-info/WHEEL
labelops-0.0.0.dist-info/top_level.txt
labelops-0.0.0.dist-info/RECORD
